fsdc/__init__.py
fsdc/fsdc.py
fsdc-0.1.8.dist-info/LICENSE
fsdc-0.1.8.dist-info/METADATA
fsdc-0.1.8.dist-info/WHEEL
fsdc-0.1.8.dist-info/entry_points.txt
fsdc-0.1.8.dist-info/top_level.txt
fsdc-0.1.8.dist-info/RECORD
