Metadata-Version: 2.1
Name: fsdc
Version: 0.1.8
Summary: Finds identical, different and unique files in 2 folders and all subfolders
Home-page: https://github.com/thiloschild/FSDC
Author: Thilo Schild
Author-email: work@thilo-schild.de
License: MIT
Platform: UNKNOWN
Classifier: Programming Language :: Python :: 3
Classifier: License :: OSI Approved :: MIT License
Classifier: Operating System :: OS Independent
Requires-Python: >=3.6
Requires-Dist: pandas
Requires-Dist: easygui
Requires-Dist: wxPython
